rnanorm/__init__.py
rnanorm/annotation.py
rnanorm/cli.py
rnanorm/datasets.py
rnanorm/typing.py
rnanorm/files/gencode.v26.annotation.chr21.gtf.gz
rnanorm/files/gtex_lung.first30.chr21.csv.gz
rnanorm/files/prepare_gtex.py
rnanorm/files/toy.gtf
rnanorm/files/toy_exp.csv
rnanorm/methods/__init__.py
rnanorm/methods/between_sample.py
rnanorm/methods/utils.py
rnanorm/methods/within_sample.py
rnanorm-2.2.0.dist-info/LICENSE
rnanorm-2.2.0.dist-info/METADATA
rnanorm-2.2.0.dist-info/WHEEL
rnanorm-2.2.0.dist-info/entry_points.txt
rnanorm-2.2.0.dist-info/top_level.txt
rnanorm-2.2.0.dist-info/RECORD
