Metadata-Version: 2.2
Name: rnanorm
Version: 2.2.0
Summary: Common RNA-seq normalization methods
Author: Genialis, Inc.
Author-email: dev-team@genialis.com
License: 
Project-URL: repository, https://github.com/genialis/RNAnorm
Keywords: bio,bioinformatics,data science,machine learning,artificial intelligence,python,genialis,rnaseq,normalization
Classifier: Development Status :: 5 - Production/Stable
Classifier: Environment :: Console
Classifier: Intended Audience :: Developers
Classifier: Topic :: Software Development :: Libraries :: Python Modules
Classifier: License :: OSI Approved :: Apache Software License
Classifier: Operating System :: OS Independent
Classifier: Programming Language :: Python
Classifier: Programming Language :: Python :: 3
Classifier: Programming Language :: Python :: 3.9
Classifier: Programming Language :: Python :: 3.10
Classifier: Programming Language :: Python :: 3.11
Classifier: Programming Language :: Python :: 3.12
Classifier: Programming Language :: Python :: 3.13
Requires-Python: <3.14,>=3.9
License-File: LICENSE
Requires-Dist: click
Requires-Dist: numpy>=1.0.0
Requires-Dist: pandas>=1.0.0
Requires-Dist: scikit-learn>=1.6.0
Requires-Dist: pandera
Provides-Extra: docs
Requires-Dist: sphinx>=5.1.1; extra == "docs"
Requires-Dist: sphinx-autodoc-typehints>=1.19.2; extra == "docs"
Provides-Extra: package
Requires-Dist: build>=0.8.0; extra == "package"
Requires-Dist: check-manifest>=0.48; extra == "package"
Requires-Dist: twine>=4.0.1; extra == "package"
Provides-Extra: test
Requires-Dist: black; extra == "test"
Requires-Dist: flake8; extra == "test"
Requires-Dist: isort; extra == "test"
Requires-Dist: mypy; extra == "test"
Requires-Dist: pydocstyle[toml]; extra == "test"
Requires-Dist: pytest; extra == "test"
Requires-Dist: pytest-cov; extra == "test"
